snn_pipeline/__init__.py
snn_pipeline/synetbuild.py
snn_pipeline/synetcontext.py
snn_pipeline/synetfind.py
snn_pipeline/synetmapping.py
snn_pipeline/synetprefix.py
snn_pipeline-0.2.5.dist-info/LICENSE
snn_pipeline-0.2.5.dist-info/METADATA
snn_pipeline-0.2.5.dist-info/WHEEL
snn_pipeline-0.2.5.dist-info/entry_points.txt
snn_pipeline-0.2.5.dist-info/top_level.txt
snn_pipeline-0.2.5.dist-info/RECORD
